MANIFEST.in
requirements.txt
setup.cfg
setup.py
napalm_nxos/__init__.py
napalm_nxos/nxos.py
napalm_nxos.egg-info/PKG-INFO
napalm_nxos.egg-info/SOURCES.txt
napalm_nxos.egg-info/dependency_links.txt
napalm_nxos.egg-info/requires.txt
napalm_nxos.egg-info/top_level.txt
napalm_nxos/templates/delete_ntp_peers.j2
napalm_nxos/templates/delete_ntp_servers.j2
napalm_nxos/templates/delete_snmp_config.j2
napalm_nxos/templates/delete_users.j2
napalm_nxos/templates/set_hostname.j2
napalm_nxos/templates/set_ntp_peers.j2
napalm_nxos/templates/set_ntp_servers.j2
napalm_nxos/templates/set_users.j2
napalm_nxos/templates/snmp_config.j2
napalm_nxos/utils/__init__.py
napalm_nxos/utils/textfsm_templates/lldp_neighbors.tpl
napalm_nxos/utils/textfsm_templates/snmp_config.tpl
napalm_nxos/utils/textfsm_templates/users.tpl
napalm_nxos_ssh/__init__.py
napalm_nxos_ssh/nxos_ssh.py
napalm_nxos_ssh/templates/delete_ntp_peers.j2
napalm_nxos_ssh/templates/delete_ntp_servers.j2
napalm_nxos_ssh/templates/delete_snmp_config.j2
napalm_nxos_ssh/templates/delete_users.j2
napalm_nxos_ssh/templates/set_hostname.j2
napalm_nxos_ssh/templates/set_ntp_peers.j2
napalm_nxos_ssh/templates/set_ntp_servers.j2
napalm_nxos_ssh/templates/set_users.j2
napalm_nxos_ssh/templates/snmp_config.j2
napalm_nxos_ssh/utils/__init__.py
napalm_nxos_ssh/utils/textfsm_templates/lldp_neighbors.tpl
napalm_nxos_ssh/utils/textfsm_templates/snmp_config.tpl
napalm_nxos_ssh/utils/textfsm_templates/users.tpl